langchain_maritaca/__init__.py
langchain_maritaca/callbacks.py
langchain_maritaca/chat_models.py
langchain_maritaca/embeddings.py
langchain_maritaca/py.typed
langchain_maritaca/version.py
langchain_maritaca-0.4.1.dist-info/METADATA
langchain_maritaca-0.4.1.dist-info/WHEEL
langchain_maritaca-0.4.1.dist-info/licenses/LICENSE
langchain_maritaca-0.4.1.dist-info/RECORD
