Metadata-Version: 2.4
Name: langchain-maritaca
Version: 0.4.1
Summary: An integration package connecting Maritaca AI and LangChain for Brazilian Portuguese language models
Project-URL: Homepage, https://github.com/anderson-ufrj/langchain-maritaca
Project-URL: Documentation, https://github.com/anderson-ufrj/langchain-maritaca#readme
Project-URL: Repository, https://github.com/anderson-ufrj/langchain-maritaca
Project-URL: Issues, https://github.com/anderson-ufrj/langchain-maritaca/issues
Project-URL: Changelog, https://github.com/anderson-ufrj/langchain-maritaca/blob/main/CHANGELOG.md
Project-URL: Maritaca AI, https://www.maritaca.ai/
Author-email: Anderson Henrique da Silva <andersonhs27@gmail.com>
License: MIT
License-File: LICENSE
Keywords: ai,brazilian,chatbot,langchain,llm,maritaca,nlp,portuguese,sabia
Classifier: Development Status :: 4 - Beta
Classifier: Intended Audience :: Developers
Classifier: License :: OSI Approved :: MIT License
Classifier: Operating System :: OS Independent
Classifier: Programming Language :: Python :: 3
Classifier: Programming Language :: Python :: 3.10
Classifier: Programming Language :: Python :: 3.11
Classifier: Programming Language :: Python :: 3.12
Classifier: Programming Language :: Python :: 3.13
Classifier: Topic :: Scientific/Engineering :: Artificial Intelligence
Classifier: Topic :: Software Development :: Libraries :: Python Modules
Requires-Python: <4.0,>=3.10
Requires-Dist: httpx<1.0.0,>=0.25.0
Requires-Dist: langchain-core<2.0.0,>=0.3.0
Provides-Extra: dev
Requires-Dist: mypy<2.0.0,>=1.10.0; extra == 'dev'
Requires-Dist: pre-commit<5.0.0,>=3.0.0; extra == 'dev'
Requires-Dist: pytest-asyncio<1.0.0,>=0.21.1; extra == 'dev'
Requires-Dist: pytest-cov<6.0.0,>=4.0.0; extra == 'dev'
Requires-Dist: pytest-mock<4.0.0,>=3.10.0; extra == 'dev'
Requires-Dist: pytest<9.0.0,>=7.3.0; extra == 'dev'
Requires-Dist: respx<1.0.0,>=0.20.0; extra == 'dev'
Requires-Dist: ruff<1.0.0,>=0.8.0; extra == 'dev'
Provides-Extra: test
Requires-Dist: pytest-asyncio<1.0.0,>=0.21.1; extra == 'test'
Requires-Dist: pytest-cov<6.0.0,>=4.0.0; extra == 'test'
Requires-Dist: pytest-mock<4.0.0,>=3.10.0; extra == 'test'
Requires-Dist: pytest<9.0.0,>=7.3.0; extra == 'test'
Requires-Dist: respx<1.0.0,>=0.20.0; extra == 'test'
Provides-Extra: tokenizer
Requires-Dist: tiktoken<1.0.0,>=0.5.0; extra == 'tokenizer'
